radiomics/__init__.py
radiomics/_cmatrices.cp38-win_amd64.pyd
radiomics/_cshape.cp38-win_amd64.pyd
radiomics/_version.py
radiomics/base.py
radiomics/featureextractor.py
radiomics/firstorder.py
radiomics/generalinfo.py
radiomics/glcm.py
radiomics/gldm.py
radiomics/glrlm.py
radiomics/glszm.py
radiomics/imageoperations.py
radiomics/ngtdm.py
radiomics/shape.py
radiomics/shape2D.py
radiomics/schemas/paramSchema.yaml
radiomics/schemas/schemaFuncs.py
radiomics/scripts/__init__.py
radiomics/scripts/segment.py
radiomics/scripts/voxel.py
pyradiomics-3.1.0.dist-info/LICENSE.txt
pyradiomics-3.1.0.dist-info/METADATA
pyradiomics-3.1.0.dist-info/WHEEL
pyradiomics-3.1.0.dist-info/top_level.txt
pyradiomics-3.1.0.dist-info/RECORD
