Metadata-Version: 2.1
Name: pyradiomics
Version: 3.1.0
Summary: Radiomics features library for python
Home-page: UNKNOWN
License: 3-Clause BSD
Platform: UNKNOWN
Requires-Dist: numpy
Requires-Dist: SimpleITK
Requires-Dist: PyWavelets
Requires-Dist: pykwalify
Requires-Dist: six
